cmpx/__init__.py
cmpx/error.py
cmpx/number.py
cmpx/equations/__init__.py
cmpx/equations/solve.py
cmpx-0.8.4.dist-info/LICENSE
cmpx-0.8.4.dist-info/METADATA
cmpx-0.8.4.dist-info/WHEEL
cmpx-0.8.4.dist-info/top_level.txt
cmpx-0.8.4.dist-info/RECORD
