Metadata-Version: 2.1
Name: cmpx
Version: 0.8.4
Summary: A package for different operations on complex numbers
Home-page: https://github.com/Omar-Belghaouti/PythonComplex
Author: Omar Belghaouti
Author-email: bel_omar18@yahoo.com
Maintainer: Omar Belghaouti
Maintainer-email: bel_omar18@yahoo.com
License: MIT
Download-URL: https://pypi.org/project/cmpx/
Keywords: Complex,ComplexOperations,ComplexNumbers
Platform: UNKNOWN
Classifier: Operating System :: OS Independent
Classifier: License :: OSI Approved :: MIT License
Classifier: Intended Audience :: End Users/Desktop
Classifier: Intended Audience :: Developers
Classifier: Programming Language :: Python :: 3
Requires-Python: ~=3.3
Requires-Dist: colorama
